MANIFEST.in
setup.cfg
setup.py
versioneer.py
pygdf/__init__.py
pygdf/_version.py
pygdf/cudautils.py
pygdf/dataframe.py
pygdf/gpuarrow.py
pygdf/reduction.py
pygdf/utils.py
pygdf.egg-info/PKG-INFO
pygdf.egg-info/SOURCES.txt
pygdf.egg-info/dependency_links.txt
pygdf.egg-info/requires.txt
pygdf.egg-info/top_level.txt
pygdf/sorting/__init__.py
pygdf/sorting/common.py
pygdf/sorting/radixsort.py
pygdf/tests/__init__.py
pygdf/tests/test_dataframe.py
pygdf/tests/test_gpu_arrow_parser.py
pygdf/tests/test_onehot.py
pygdf/tests/test_sparse_df.py
pygdf/tests/test_stats.py