Metadata-Version: 1.1
Name: pygdf
Version: 0.1.0a1
Summary: GPU Dataframe
Home-page: UNKNOWN
Author: Continuum Analytics, Inc.
Author-email: UNKNOWN
License: BSD
Platform: UNKNOWN
Classifier: Intended Audience :: Developers
Classifier: Programming Language :: Python
Classifier: Programming Language :: Python :: 3.5
